README.txt
setup.py
jenkviz/__init__.py
jenkviz/build.py
jenkviz/command.py
jenkviz/crawl.py
jenkviz/graphviz.py
jenkviz/main.py
jenkviz/model.py
jenkviz/util.py
jenkviz.egg-info/PKG-INFO
jenkviz.egg-info/SOURCES.txt
jenkviz.egg-info/dependency_links.txt
jenkviz.egg-info/entry_points.txt
jenkviz.egg-info/requires.txt
jenkviz.egg-info/top_level.txt
jenkviz.egg-info/zip-safe