Metadata-Version: 1.1
Name: jenkviz
Version: 0.3.2
Summary: Crawl a jenkins build and report stats and graphs about the build flow.
Home-page: http://pypi.python.org/pypi/jenkviz
Author: Benoit Delbosc
Author-email: bdelbosc@nuxeo.com
License: GPL
Download-URL: http://pypi.python.org/packages/source/t/jenkviz/jenkviz-0.3.2.tar.gz
Keywords: jenkins hudson CI chart
Platform: UNKNOWN
Classifier: Development Status :: 4 - Beta
Classifier: Environment :: Console
Classifier: Intended Audience :: Developers
Classifier: Intended Audience :: Information Technology
Classifier: Intended Audience :: System Administrators
Classifier: Natural Language :: English
Classifier: License :: OSI Approved :: GNU General Public License (GPL)
Classifier: Operating System :: OS Independent
Classifier: Programming Language :: Python
Classifier: Topic :: Software Development :: Quality Assurance
